[{"id": "pcQjfBFdQmn6Aqep1PKrAJ8tpZY=", "ratings": {"Overall Rating": "Liked it!", "Riding Style": "All Mountain Freestyle", "Riding Level": "Beginner - Expert", "Fits Boot size (US)": "8-10", "Manufactured in": "Tunisia by Nidecker", "Shape": "True Twin", "Camber Profile": "Hybrid Camber", "Stance": "Centered", "Approx. Weight": "Feels Normal", "Powder": "Average", "Turning": "Experience", "Carving": "Good", "Speed": "Great", "Uneven": "Terrain", "Switch": "Great", "Jumps": "Good", "Jibbing": "Average", "Pipe": "Great", "On": "Snow", "Turn": "Initiation", "Skidded": "Turns", "Flex": "Medium", "Buttering": "Semi-Easy", "Edge": "Hold"}, "meta_data": {"name": "alloy-b-bomb-2016-2020-snowboard-review", "gender": "mens", "url": "https://thegoodride.com/snowboard-reviews/alloy-b-bomb-2016-2020-snowboard-review", "price": "$549", "image_url": "https://thegoodride.com/assets/lg-gallery/alloy/snowboards/b-bomb/alloy-b-bomb.jpg"}}, {"id": "WdfFXZW/dvMLdhtMZs3ihVDCRHI=", "ratings": {"Overall Rating": "", "Riding Style": "Freestyle", "Riding Level": "Intermediate - Expert", "Fits Boot size (US)": "8-10", "Manufactured in": "Tunisia by Nidecker", "Shape": "True Twin", "Camber Profile": "Hybrid Camber", "Stance": "Centered", "Approx. Weight": "Feels Normal", "Powder": "Average", "Turning": "Experience", "Carving": "Average", "Speed": "Average", "Uneven": "Terrain", "Switch": "Great", "Jumps": "Good", "Jibbing": "Great", "Pipe": "Good", "On": "Snow", "Turn": "Initiation", "Skidded": "Turns", "Flex": "Medium/Soft", "Buttering": "Easy", "Edge": "Hold"}, "meta_data": {"name": "alloy-b-bomb-gt-2020-snowboard-review", "gender": "mens", "url": "https://thegoodride.com/snowboard-reviews/alloy-b-bomb-gt-2020-snowboard-review", "price": "$0", "image_url": "https://thegoodride.com/assets/lg-gallery/alloy/snowboards/b-bomb-gt/alloy-b-bomb-gt.jpg"}}, {"id": "GLXwggrHSpW/E/vBriKPps5WPmE=", "ratings": {"Overall Rating": "Pretty Good", "Riding Style": "Freeride", "Riding Level": "Expert", "Fits Boot size (US)": "8-10", "Manufactured in": "Tunisia by Nidecker", "Shape": "Tapered Directional", "Camber Profile": "Traditional Camber", "Stance": "Setback over 20mm", "Approx. Weight": "Feels Heavy", "Powder": "Poor", "Turning": "Experience", "Carving": "Excellent", "Speed": "Excellent", "Uneven": "Terrain", "Switch": "Average", "Jumps": "Good", "Jibbing": "Poor", "Pipe": "Poor", "On": "Snow", "Turn": "Initiation", "Skidded": "Turns", "Flex": "Stiff", "Buttering": "Hard", "Edge": "Hold"}, "meta_data": {"name": "alloy-d-o-carbon-2019-2020-snowboard-review", "gender": "mens", "url": "https://thegoodride.com/snowboard-reviews/alloy-d-o-carbon-2019-2020-snowboard-review", "price": "$999", "image_url": "https://thegoodride.com/assets/lg-gallery/alloy/snowboards/d-o-carbon/alloy-d-o-carbon.jpg"}}, {"id": "vyqJS+sM6x2avNeKZCtTt6aTMlA=", "ratings": {"Overall Rating": "", "Riding Style": "Alternative Freeride", "Riding Level": "Advanced - Expert", "Fits Boot size (US)": "8-10", "Manufactured in": "Tunisia by Nidecker", "Shape": "Tapered Directional", "Camber Profile": "Directional Camber", "Stance": "Setback over 20mm", "Approx. Weight": "Feels Normal", "Powder": "Good", "Turning": "Experience", "Carving": "Great", "Speed": "Great", "Uneven": "Terrain", "Switch": "Poor", "Jumps": "Average", "Jibbing": "Poor", "Pipe": "Average", "On": "Snow", "Turn": "Initiation", "Skidded": "Turns", "Flex": "Medium/Stiff", "Buttering": "Semi-Hard", "Edge": "Hold"}, "meta_data": {"name": "alloy-darwin-flow-2020-snowboard-review", "gender": "mens", "url": "https://thegoodride.com/snowboard-reviews/alloy-darwin-flow-2020-snowboard-review", "price": "$0", "image_url": "https://thegoodride.com/assets/lg-gallery/alloy/snowboards/darwin-flow/alloy-darwin-flow.jpg"}}, {"id": "IbVxVGqf7kOWjwmJu3U0lxr16gk=", "ratings": {"Overall Rating": "Liked it!", "Riding Style": "Freeride", "Riding Level": "Expert", "Fits Boot size (US)": "8-10", "Manufactured in": "Tunisia by Nidecker", "Shape": "Tapered Directional", "Camber Profile": "Mostly Camber", "Stance": "Setback over 20mm", "Approx. Weight": "Feels Normal", "Powder": "Poor", "Turning": "Experience", "Carving": "Excellent", "Speed": "Great", "Uneven": "Terrain", "Switch": "Average", "Jumps": "Average", "Jibbing": "Poor", "Pipe": "Poor", "On": "Snow", "Turn": "Initiation", "Skidded": "Turns", "Flex": "Medium/Stiff", "Buttering": "Hard", "Edge": "Hold"}, "meta_data": {"name": "alloy-do-7x-2017-snowboard-review", "gender": "mens", "url": "https://thegoodride.com/snowboard-reviews/alloy-do-7x-2017-snowboard-review", "price": "$749", "image_url": "https://thegoodride.com/assets/lg-gallery/alloy/snowboards/do-7x/alloy-do-7x.jpg"}}, {"id": "7j4iqh428rEvYvOboeaeLtnxYI0=", "ratings": {"Overall Rating": "Liked it!", "Riding Style": "Freeride", "Riding Level": "Expert", "Fits Boot size (US)": "8-10", "Manufactured in": "Tunisia by Nidecker", "Shape": "Tapered Directional", "Camber Profile": "Traditional Camber", "Stance": "Setback over 20mm", "Approx. Weight": "Feels Normal", "Powder": "Poor", "Turning": "Experience", "Carving": "Excellent", "Speed": "Great", "Uneven": "Terrain", "Switch": "Average", "Jumps": "Average", "Jibbing": "Poor", "Pipe": "Poor", "On": "Snow", "Turn": "Initiation", "Skidded": "Turns", "Flex": "Medium/Stiff", "Buttering": "Hard", "Edge": "Hold"}, "meta_data": {"name": "alloy-do-bc-2017-snowboard-review", "gender": "mens", "url": "https://thegoodride.com/snowboard-reviews/alloy-do-bc-2017-snowboard-review", "price": "$839", "image_url": "https://thegoodride.com/assets/lg-gallery/alloy/snowboards/do-bc/alloy-do-bc.jpg"}}, {"id": "3CW9TTqpy7zqLJ9BrXQClPA7PPU=", "ratings": {"Overall Rating": "", "Riding Style": "All Mountain", "Riding Level": "Advanced - Expert", "Fits Boot size (US)": "8-10", "Manufactured in": "Tunisia by Nidecker", "Shape": "Directional Twin", "Camber Profile": "Traditional Camber", "Stance": "Setback -10mm", "Approx. Weight": "Feels Normal", "Powder": "Poor", "Turning": "Experience", "Carving": "Great", "Speed": "Great", "Uneven": "Terrain", "Switch": "Great", "Jumps": "Great", "Jibbing": "Average", "Pipe": "Great", "On": "Snow", "Turn": "Initiation", "Skidded": "Turns", "Flex": "Medium", "Buttering": "Moderate", "Edge": "Hold"}, "meta_data": {"name": "alloy-kwang-ki-2020-snowboard-reveiw", "gender": "mens", "url": "https://thegoodride.com/snowboard-reviews/alloy-kwang-ki-2020-snowboard-reveiw", "price": "$549", "image_url": "https://thegoodride.com/assets/lg-gallery/alloy/snowboards/kwang-ki/alloy-kwang-ki.jpg"}}, {"id": "X5VwiII0xXn75VZTMIF349GtiI8=", "ratings": {"Overall Rating": "Liked it!", "Riding Style": "All Mountain", "Riding Level": "Advanced - Expert", "Fits Boot size (US)": "8-10", "Manufactured in": "Tunisia by Nidecker", "Shape": "Directional Twin", "Camber Profile": "Mostly Camber", "Stance": "Setback -20mm", "Approx. Weight": "Feels Normal", "Powder": "Average", "Turning": "Experience", "Carving": "Great", "Speed": "Great", "Uneven": "Terrain", "Switch": "Good", "Jumps": "Great", "Jibbing": "Average", "Pipe": "Great", "On": "Snow", "Turn": "Initiation", "Skidded": "Turns", "Flex": "Medium", "Buttering": "Moderate", "Edge": "Hold"}, "meta_data": {"name": "alloy-outkome-2019-2020-snowboard-review", "gender": "mens", "url": "https://thegoodride.com/snowboard-reviews/alloy-outkome-2019-2020-snowboard-review", "price": "$499", "image_url": "https://thegoodride.com/assets/lg-gallery/alloy/snowboards/outkome/alloy-outkome.jpg"}}, {"id": "IRhS/LYoZnYU8I+waYdA7x0hZM8=", "ratings": {"Overall Rating": "Liked it!", "Riding Style": "All Mountain", "Riding Level": "Advanced - Expert", "Fits Boot size (US)": "8-10", "Manufactured in": "Tunisia by Nidecker", "Shape": "Directional", "Camber Profile": "Traditional Camber", "Stance": "Setback -20mm", "Approx. Weight": "Feels Normal", "Powder": "Average", "Turning": "Experience", "Carving": "Great", "Speed": "Great", "Uneven": "Terrain", "Switch": "Good", "Jumps": "Great", "Jibbing": "Poor", "Pipe": "Excellent", "On": "Snow", "Turn": "Initiation", "Skidded": "Turns", "Flex": "Medium/Stiff", "Buttering": "Semi-Hard", "Edge": "Hold"}, "meta_data": {"name": "alloy-sniper-2016-2020-snowboard-review", "gender": "mens", "url": "https://thegoodride.com/snowboard-reviews/alloy-sniper-2016-2020-snowboard-review", "price": "$649", "image_url": "https://thegoodride.com/assets/lg-gallery/alloy/snowboards/sniper/alloy-sniper.jpg"}}, {"id": "V8LdwsXcvVQ4Inile9zTx1Ghtc0=", "ratings": {"Overall Rating": "Liked it!", "Riding Style": "Freeride", "Riding Level": "Advanced - Expert", "Fits Boot size (US)": "8-10, 10-12, > 12", "Manufactured in": "Dubai by SWS", "Shape": "Tapered Directional", "Camber Profile": "Mostly Camber", "Stance": "Setback -10mm", "Approx. Weight": "Feels Normal", "Powder": "Good", "Turning": "Experience", "Carving": "Excellent", "Speed": "Excellent", "Uneven": "Terrain", "Switch": "Poor", "Jumps": "Average", "Jibbing": "Poor", "Pipe": "Average", "On": "Snow", "Turn": "Initiation", "Skidded": "Turns", "Flex": "Stiff", "Buttering": "Hard", "Edge": "Hold"}, "meta_data": {"name": "arbor-a-frame-2010-2019-snowboard-review", "gender": "mens", "url": "https://thegoodride.com/snowboard-reviews/arbor-a-frame-2010-2019-snowboard-review", "price": "$649", "image_url": "https://thegoodride.com/assets/lg-gallery/arbor/snowboards/a-frame/arbor-a-frame.jpg"}}, {"id": "IGWS3GAVSYC6QPSJWwj04JCs24Y=", "ratings": {"Overall Rating": "", "Riding Style": "Freeride", "Riding Level": "Advanced - Expert", "Fits Boot size (US)": "8-10, 10-12", "Manufactured in": "Dubai by SWS", "Shape": "Tapered Directional", "Camber Profile": "Mostly Camber", "Stance": "Setback -10mm", "Approx. Weight": "Feels Normal", "Powder": "Good", "Turning": "Experience", "Carving": "Great", "Speed": "Great", "Uneven": "Terrain", "Switch": "Average", "Jumps": "Good", "Jibbing": "Poor", "Pipe": "Good", "On": "Snow", "Turn": "Initiation", "Skidded": "Turns", "Flex": "Stiff", "Buttering": "Hard", "Edge": "Hold"}, "meta_data": {"name": "arbor-annex-2021-snowboard-review", "gender": "mens", "url": "https://thegoodride.com/snowboard-reviews/arbor-annex-2021-snowboard-review", "price": "$699", "image_url": "https://thegoodride.com/assets/lg-gallery/arbor/snowboards/annex/arbor-annex.jpg"}}, {"id": "49q5/R4aizM1/UbGwtxs9Rt8k58=", "ratings": {"Overall Rating": "", "Riding Style": "All Mountain", "Riding Level": "Intermediate - Expert", "Fits Boot size (US)": "8-10", "Manufactured in": "Dubai by SWS", "Shape": "Tapered Directional", "Camber Profile": "Mostly Camber", "Stance": "Centered", "Approx. Weight": "Feels Normal", "Powder": "Average", "Turning": "Experience", "Carving": "Great", "Speed": "Great", "Uneven": "Terrain", "Switch": "Good", "Jumps": "Great", "Jibbing": "Poor", "Pipe": "Great", "On": "Snow", "Turn": "Initiation", "Skidded": "Turns", "Flex": "Medium/Stiff", "Buttering": "Semi-Hard", "Edge": "Hold"}, "meta_data": {"name": "arbor-bryan-iguchi-pro-camber-2017-2021-snowboard-review", "gender": "mens", "url": "https://thegoodride.com/snowboard-reviews/arbor-bryan-iguchi-pro-camber-2017-2021-snowboard-review", "price": "$599", "image_url": "https://thegoodride.com/assets/lg-gallery/arbor/snowboards/bryan-iguchi-pro-camber/arbor-bryan-iguchi-pro-camber.jpg"}}, {"id": "czEQYmldF7Sw+jL9+RtW60456qk=", "ratings": {"Overall Rating": "It\u00b4s OK", "Riding Style": "All Mountain", "Riding Level": "Beginner - Advanced", "Fits Boot size (US)": "8-10", "Manufactured in": "Dubai by SWS", "Shape": "Tapered Directional", "Camber Profile": "Continuous Rocker", "Stance": "Centered", "Approx. Weight": "Feels Normal", "Powder": "Good", "Turning": "Experience", "Carving": "Average", "Speed": "Average", "Uneven": "Terrain", "Switch": "Good", "Jumps": "Good", "Jibbing": "Good", "Pipe": "Good", "On": "Snow", "Turn": "Initiation", "Skidded": "Turns", "Flex": "Medium", "Buttering": "Semi-Easy", "Edge": "Hold"}, "meta_data": {"name": "arbor-bryan-iguchi-pro-rocker-snowboard-review", "gender": "mens", "url": "https://thegoodride.com/snowboard-reviews/arbor-bryan-iguchi-pro-rocker-snowboard-review", "price": "$549", "image_url": "https://thegoodride.com/assets/lg-gallery/arbor/snowboards/bryan-iguchi-pro-rocker/arbor-bryan-iguchi-pro-rocker.jpg"}}, {"id": "N2X1VyOC7WbzdfPHsQY/qmMB3mc=", "ratings": {"Overall Rating": "Pretty Good", "Riding Style": "Alternative Freeride", "Riding Level": "Intermediate - Expert", "Fits Boot size (US)": "8-10, 10-12", "Manufactured in": "Dubai by SWS", "Shape": "Tapered Directional", "Camber Profile": "Mostly Camber", "Stance": "Centered", "Approx. Weight": "Feels Heavy", "Powder": "Great", "Turning": "Experience", "Carving": "Good", "Speed": "Good", "Uneven": "Terrain", "Switch": "Poor", "Jumps": "Average", "Jibbing": "Poor", "Pipe": "Good", "On": "Snow", "Turn": "Initiation", "Skidded": "Turns", "Flex": "Medium/Stiff", "Buttering": "Semi-Hard", "Edge": "Hold"}, "meta_data": {"name": "arbor-cask-2019-snowboard-review", "gender": "mens", "url": "https://thegoodride.com/snowboard-reviews/arbor-cask-2019-snowboard-review", "price": "$499", "image_url": "https://thegoodride.com/assets/lg-gallery/arbor/snowboards/cask/arbor-cask.jpg"}}, {"id": "+76gNyVnBLBdJYe+pAXciVJ+kCk=", "ratings": {"Overall Rating": "Not for us", "Riding Style": "Freeride", "Riding Level": "Intermediate - Expert", "Fits Boot size (US)": "< 8, 8-10", "Manufactured in": "Dubai by SWS", "Shape": "Tapered Directional", "Camber Profile": "Mostly Camber", "Stance": "Centered", "Approx. Weight": "Feels Heavy", "Powder": "Good", "Turning": "Experience", "Carving": "Good", "Speed": "Good", "Uneven": "Terrain", "Switch": "Good", "Jumps": "Good", "Jibbing": "Average", "Pipe": "Good", "On": "Snow", "Turn": "Initiation", "Skidded": "Turns", "Flex": "Medium/Stiff", "Buttering": "Semi-Hard", "Edge": "Hold"}, "meta_data": {"name": "arbor-clovis-2017-2019-snowboard-review", "gender": "mens", "url": "https://thegoodride.com/snowboard-reviews/arbor-clovis-2017-2019-snowboard-review", "price": "$499", "image_url": "https://thegoodride.com/assets/lg-gallery/arbor/snowboards/clovis/arbor-clovis.jpg"}}, {"id": "+FbeaX6Jo3bC5sDgql1p9ev4qCw=", "ratings": {"Overall Rating": "Liked it!", "Riding Style": "All Mountain Freestyle", "Riding Level": "Intermediate - Expert", "Fits Boot size (US)": "8-10", "Manufactured in": "Dubai by SWS", "Shape": "Directional Twin", "Camber Profile": "Mostly Camber", "Stance": "Centered", "Approx. Weight": "Feels Normal", "Powder": "Average", "Turning": "Experience", "Carving": "Great", "Speed": "Good", "Uneven": "Terrain", "Switch": "Great", "Jumps": "Excellent", "Jibbing": "Good", "Pipe": "Great", "On": "Snow", "Turn": "Initiation", "Skidded": "Turns", "Flex": "Medium", "Buttering": "Moderate", "Edge": "Hold"}, "meta_data": {"name": "arbor-coda-camber-2016-2019-snowboard-review", "gender": "mens", "url": "https://thegoodride.com/snowboard-reviews/arbor-coda-camber-2016-2019-snowboard-review", "price": "$499", "image_url": "https://thegoodride.com/assets/lg-gallery/arbor/snowboards/coda-camber/arbor-coda-camber.jpg"}}, {"id": "xGarud1QzhGT3iw/OWIzMRhKmu8=", "ratings": {"Overall Rating": "Pretty Good", "Riding Style": "Powder", "Riding Level": "Beginner - Advanced", "Fits Boot size (US)": "8-10", "Manufactured in": "Dubai by SWS", "Shape": "Tapered Directional", "Camber Profile": "Continuous Rocker", "Stance": "Setback -20mm", "Approx. Weight": "Feels Normal", "Powder": "Great", "Turning": "Experience", "Carving": "Average", "Speed": "Good", "Uneven": "Terrain", "Switch": "Average", "Jumps": "Average", "Jibbing": "Average", "Pipe": "Average", "On": "Snow", "Turn": "Initiation", "Skidded": "Turns", "Flex": "Medium/Stiff", "Buttering": "Semi-Easy", "Edge": "Hold"}, "meta_data": {"name": "arbor-cosa-nostra-2017-snowboard-review", "gender": "mens", "url": "https://thegoodride.com/snowboard-reviews/arbor-cosa-nostra-2017-snowboard-review", "price": "$599", "image_url": "https://thegoodride.com/assets/lg-gallery/arbor/snowboards/cosa-nostra/arbor-cosa-nostra.jpg"}}, {"id": "QhcuswUxH33rf5I1ClysWFhzZuo=", "ratings": {"Overall Rating": "", "Riding Style": "Freeride", "Riding Level": "Advanced - Expert", "Fits Boot size (US)": "8-10, 10-12, > 12", "Manufactured in": "Dubai by SWS", "Shape": "Tapered Directional", "Camber Profile": "Mostly Camber", "Stance": "Setback -10mm", "Approx. Weight": "Feels Normal", "Powder": "Good", "Turning": "Experience", "Carving": "Great", "Speed": "Great", "Uneven": "Terrain", "Switch": "Average", "Jumps": "Good", "Jibbing": "Poor", "Pipe": "Poor", "On": "Snow", "Turn": "Initiation", "Skidded": "Turns", "Flex": "Medium/Stiff", "Buttering": "Semi-Hard", "Edge": "Hold"}, "meta_data": {"name": "arbor-crosscut-camber-2021-snowboard-review", "gender": "mens", "url": "https://thegoodride.com/snowboard-reviews/arbor-crosscut-camber-2021-snowboard-review", "price": "$499", "image_url": "https://thegoodride.com/assets/lg-gallery/arbor/snowboards/crosscut-camber/arbor-crosscut-camber.jpg"}}, {"id": "LVjOY/cS93dg+0X5yGvu4411FMM=", "ratings": {"Overall Rating": "Liked it!", "Riding Style": "All Mountain Freestyle", "Riding Level": "Intermediate - Expert", "Fits Boot size (US)": "8-10", "Manufactured in": "Dubai by SWS", "Shape": "Directional Twin", "Camber Profile": "Continuous Rocker", "Stance": "Centered", "Approx. Weight": "Feels Normal", "Powder": "Average", "Turning": "Experience", "Carving": "Average", "Speed": "Good", "Uneven": "Terrain", "Switch": "Great", "Jumps": "Great", "Jibbing": "Good", "Pipe": "Good", "On": "Snow", "Turn": "Initiation", "Skidded": "Turns", "Flex": "Medium", "Buttering": "Easy", "Edge": "Hold"}, "meta_data": {"name": "arbor-element-2010-2017-snowboard-review", "gender": "mens", "url": "https://thegoodride.com/snowboard-reviews/arbor-element-2010-2017-snowboard-review", "price": "$529", "image_url": "https://thegoodride.com/assets/lg-gallery/arbor/snowboards/element/arbor-element.jpg"}}, {"id": "SRC+4Wjo+l1DZ4hWHeOp0nVer5k=", "ratings": {"Overall Rating": "", "Riding Style": "All Mountain Freestyle", "Riding Level": "Intermediate - Expert", "Fits Boot size (US)": "8-10, 10-12", "Manufactured in": "Dubai by SWS", "Shape": "Directional Twin", "Camber Profile": "Mostly Camber", "Stance": "Centered", "Approx. Weight": "Feels Normal", "Powder": "Poor", "Turning": "Experience", "Carving": "Great", "Speed": "Great", "Uneven": "Terrain", "Switch": "Great", "Jumps": "Great", "Jibbing": "Average", "Pipe": "Great", "On": "Snow", "Turn": "Initiation", "Skidded": "Turns", "Flex": "Medium", "Buttering": "Moderate", "Edge": "Hold"}, "meta_data": {"name": "arbor-element-camber-2021-snowboard-review", "gender": "mens", "url": "https://thegoodride.com/snowboard-reviews/arbor-element-camber-2021-snowboard-review", "price": "$449", "image_url": "https://thegoodride.com/assets/lg-gallery/arbor/snowboards/element-camber/arbor-element-camber.jpg"}}]